flickr_sdc/__init__.py
flickr_sdc/_types.py
flickr_sdc/flickr_user_ids.py
flickr_sdc/py.typed
flickr_sdc/structured_data.py
flickr_sdc/utils.py
flickr_sdc/wikidata.py
flickr_sdc/wikimedia.py
flickr_sdc-1.0.0.dist-info/LICENSE-APACHE
flickr_sdc-1.0.0.dist-info/LICENSE-MIT
flickr_sdc-1.0.0.dist-info/METADATA
flickr_sdc-1.0.0.dist-info/WHEEL
flickr_sdc-1.0.0.dist-info/top_level.txt
flickr_sdc-1.0.0.dist-info/RECORD
