Metadata-Version: 2.1
Name: flickr-sdc
Version: 1.0.0
Summary: Structured data definitions for Flickr photos on Wikimedia Commons
Author-email: Flickr Foundation <hello@flickr.org>
Maintainer-email: Alex Chan <alex@flickr.org>
Project-URL: Homepage, https://github.com/Flickr-Foundation/flickr-sdc
Project-URL: Changelog, https://github.com/Flickr-Foundation/flickr-sdc/blob/main/CHANGELOG.md
Keywords: flickr,wikimedia_commons
Classifier: Development Status :: 5 - Production/Stable
Classifier: License :: OSI Approved :: Apache Software License
Classifier: License :: OSI Approved :: MIT License
Classifier: Programming Language :: Python :: 3.12
Requires-Python: >=3.2
License-File: LICENSE-APACHE
License-File: LICENSE-MIT
Requires-Dist: flickr-photos-api >=1.2.0
Requires-Dist: httpx
Requires-Dist: pydantic
